onoffServices/__init__.py
onoffServices/ec2.py
onoffServices/ecs.py
onoffServices/rds.py
onoffServices-1.0.0.dist-info/METADATA
onoffServices-1.0.0.dist-info/WHEEL
onoffServices-1.0.0.dist-info/top_level.txt
onoffServices-1.0.0.dist-info/RECORD
