Metadata-Version: 2.1
Name: onoffServices
Version: 1.0.0
Summary: Aws onoff services
Author: nkundeti
Author-email: <kundeti.naveen@impressico.com>
Keywords: python,aws,onoff
Classifier: Development Status :: 1 - Planning
Classifier: Intended Audience :: Developers
Classifier: Programming Language :: Python :: 3
Classifier: Operating System :: Unix
Classifier: Operating System :: MacOS :: MacOS X
Classifier: Operating System :: Microsoft :: Windows
